<!--
  ~ The contents of this file are subject to the OpenMRS Public License
  ~ Version 1.0 (the "License"); you may not use this file except in
  ~ compliance with the License. You may obtain a copy of the License at
  ~ http://license.openmrs.org
  ~
  ~ Software distributed under the License is distributed on an "AS IS"
  ~ basis, WITHOUT WARRANTY OF ANY KIND, either express or implied. See the
  ~ License for the specific language governing rights and limitations
  ~ under the License.
  ~
  ~ Copyright (C) OpenMRS, LLC.  All Rights Reserved.
-->
<htmlform>

	<style type="text/css">
		table.hei {
		border-collapse: collapse;
		background-color: #fff0f7
		}
		table.hei > tbody > tr > td, table.hei > tbody > tr > th {
		border: 1px solid black;
		vertical-align: baseline;
		padding: 4px;
		text-align: left;
		}
	</style>
	<table border="0"  class="hei" align="center">
		<tbody>
			<tr>
				<td  style="background-color: #696969; color: #ffffff;text-align:center;">IMMUNIZATIONS(PROTECT YOUR CHILD)</td>
			</tr>
			<tr>
				<td>
					Enrollment Date <encounterDate id="encounter-date" showTime="true" />
					Name of the Facility <encounterLocation default="GlobalProperty:kenyaemr.defaultLocation" />
					Enrolled by: <encounterProviderAndRole encounterRole="a0b03050-c99b-11e0-9572-0800200c9a66" default="currentUser" required="true" />
				</td>
			</tr>
			<tr>
					<td>
						<table>
							<tr>
								<td>
									<table class="hei">
										<tbody>
											<tr>
												<th>BCG VACCINE: at birth</th>
												<th rowspan="2">Date Given</th>
												<th rowspan="2">Date of next visit</th>
											</tr>
											<tr>
												<th><i>(intra-dermal left fore arm)</i></th>
											</tr>
										</tbody>
									</table>
								</td>
								<td>
									<table class="hei">
										<tbody>
											<tr>
												<th>ORAL POLIO VACCINE(OPV)</th>
												<th rowspan="2">Date Given</th>
												<th rowspan="2">Date of next visit</th>
											</tr>
											<tr>
												<th><i>Dose: 2 drops orally</i></th>
											</tr>
										</tbody>
									</table>
								</td>
							</tr>
						</table>
					</td>
			</tr>
			<tr>
				<td style="text-align:center;">
					<div class="ke-form-footer">
						<submit />
					</div>
				</td>
			</tr>
		</tbody>
	</table>
</htmlform>